mscales/__init__.py
mscales/_version.py
mscales/basic.py
mscales/concepts.py
mscales/plots.py
mscales/scales.py
mscales/sound.py
mscales/utils.py
mscales/tests/__init__.py
mscales/tests/conftest.py
mscales/tests/test_examples.py
mscales-1.4.1.dist-info/AUTHORS.rst
mscales-1.4.1.dist-info/LICENSE
mscales-1.4.1.dist-info/METADATA
mscales-1.4.1.dist-info/WHEEL
mscales-1.4.1.dist-info/top_level.txt
mscales-1.4.1.dist-info/RECORD
