Metadata-Version: 2.1
Name: mscales
Version: 1.4.1
Summary: Python package to generate and analyze musical scales.
Home-page: https://github.com/fabianmoss/mscales
Author: Fabian C. Moss
Author-email: fabianmoss@gmail.com
License: BSD (3-clause)
Classifier: Development Status :: 2 - Pre-Alpha
Classifier: Natural Language :: English
Classifier: Programming Language :: Python :: 3
Requires-Python: >=3.7
License-File: LICENSE
License-File: AUTHORS.rst
Requires-Dist: numpy
Requires-Dist: pretty-midi
Requires-Dist: matplotlib
